{"about_index.md":"0kjRJ6nB","archives_index.md":"y5XEJjxa","index.md":"TwC2Ccmw","posts_2025_2025052701_index.md":"D75XPVH5","posts_2025_2025052702_index.md":"BKROYtwm","posts_2025_2025052703_index.md":"B1lj4OVg","posts_2025_2025070301_index.md":"B1SYrCbY","posts_2025_2025070401_index.md":"CbdH15qs","posts_2025_2025072101_index.md":"CNVqjjIo","posts_index.md":"DlwwZYPB","projects_index.md":"BHNn33zF","series_index.md":"yPta6l0p","tags_composition-api_index.md":"D0nDUnMe","tags_dify_index.md":"3uLV54Ov","tags_github-pages_index.md":"BkvSgAVc","tags_https_index.md":"Cqf64b2a","tags_index.md":"tFPdtxs7","tags_mcp_index.md":"DEF2Tb_a","tags_ubuntu_index.md":"BLPEWX7L","tags_vitepress_index.md":"B4yeFvKz","tags_vue3_index.md":"CQ5lqmm3","tags_前端_index.md":"CwvmCsAS","tags_博客_index.md":"BqJaBgyb","tags_部署_index.md":"ut2EP2-t"}
